{
    "hash": "343f0ce345410d539839bd1ad40bab1700e996b1ced37ca17e1da03dc96ecbd9",
    "inputs": [
        {
            "address": "addr1qy7nrrx7g82u2e9myd25ju0pe202rf62ees8a3l0ur7s96dmk07q3frcjqltgm38txmcrlm7eqs7mcjxqwmavgkha3lsdaxw72",
            "amount": [
                {
                    "unit": "lovelace",
                    "quantity": "517827547"
                }
            ],
            "tx_hash": "d44c12369d5483cf9e7e2d902f0c350da105e66dd086d9f3c2882f69bf4358bb",
            "output_index": 0,
            "data_hash": null,
            "inline_datum": null,
            "reference_script_hash": null,
            "collateral": false,
            "reference": false
        }
    ],
    "outputs": [
        {
            "address": "addr1qy7nrrx7g82u2e9myd25ju0pe202rf62ees8a3l0ur7s96dmk07q3frcjqltgm38txmcrlm7eqs7mcjxqwmavgkha3lsdaxw72",
            "amount": [
                {
                    "unit": "lovelace",
                    "quantity": "17639298"
                }
            ],
            "output_index": 0,
            "data_hash": null,
            "inline_datum": null,
            "collateral": false,
            "reference_script_hash": null
        }
    ]
}