{
    "hash": "4ff17aee51443fd0f04d8c56592d4fe24045c2078a84c016b1b4f89a2a40cb4f",
    "inputs": [
        {
            "address": "addr1qx3vae7d2k3rdlq3ja2uqfasqsl2l5q55qhh0lmfxqdvkz86yqn95gjt4esttt48thgugrya4mm5u8x9zzqdv4ummyyq7pwd4n",
            "amount": [
                {
                    "unit": "lovelace",
                    "quantity": "292633154"
                }
            ],
            "tx_hash": "ff44a3304cff8f1a80a1ac62c7cb703b10262f192f3e435a89c409e0148a8f36",
            "output_index": 0,
            "data_hash": null,
            "inline_datum": null,
            "reference_script_hash": null,
            "collateral": false,
            "reference": false
        }
    ],
    "outputs": [
        {
            "address": "addr1q9f95djd9tf4ka0f6vk2hpu4fkk5c8a6pr53yxtsta2jc6nx5uwa85u274prfyeyf4wepgfjc6l60jes04n2wax5eulsvnmwhe",
            "amount": [
                {
                    "unit": "lovelace",
                    "quantity": "22000000"
                }
            ],
            "output_index": 0,
            "data_hash": null,
            "inline_datum": null,
            "collateral": false,
            "reference_script_hash": null
        },
        {
            "address": "addr1q9ts963pn4v7gyg70cc82d5rjtf82uhzyl78yj9kq4ltwjh6yqn95gjt4esttt48thgugrya4mm5u8x9zzqdv4ummyyqzyu3v8",
            "amount": [
                {
                    "unit": "lovelace",
                    "quantity": "270464881"
                }
            ],
            "output_index": 1,
            "data_hash": null,
            "inline_datum": null,
            "collateral": false,
            "reference_script_hash": null
        }
    ]
}