{
    "hash": "17d778b086841d60c8216945a3b201ac1a8454aa7c3477e0fa5c5d22ff259d9c",
    "inputs": [
        {
            "address": "addr1qxg94u55v9urwaay45t4ffqsn7y9ndvzhz8y2rp3df2vvyqwq3wh8ycd3n4ulgmjsd7yg99dexmrjn5jvq02zndyl53szkgam8",
            "amount": [
                {
                    "unit": "lovelace",
                    "quantity": "23671190612"
                }
            ],
            "tx_hash": "a0bf00ffbe953c15ffeab6e08d51f4640a32606797844377b225ccd133a00c55",
            "output_index": 12,
            "data_hash": null,
            "inline_datum": null,
            "reference_script_hash": null,
            "collateral": false,
            "reference": false
        },
        {
            "address": "addr1qx6y2568ve83yy4m9qsdtx26mqgzx2pg9r4kxd6vrm6pf9cwq3wh8ycd3n4ulgmjsd7yg99dexmrjn5jvq02zndyl53scmu0w3",
            "amount": [
                {
                    "unit": "lovelace",
                    "quantity": "1097952924"
                }
            ],
            "tx_hash": "ae86283d380724cdfb2b4c7ad54f1411f4f26e013637c938952a119d4e364262",
            "output_index": 12,
            "data_hash": null,
            "inline_datum": null,
            "reference_script_hash": null,
            "collateral": false,
            "reference": false
        },
        {
            "address": "addr1qyknda6dcw6ggx6sdleav38m0qrth29zpp6xqmyjq7d8rkqwq3wh8ycd3n4ulgmjsd7yg99dexmrjn5jvq02zndyl53s9a2t9y",
            "amount": [
                {
                    "unit": "lovelace",
                    "quantity": "157913226"
                }
            ],
            "tx_hash": "ea30d22b794d7ee202af8b2db4327b15a1b7c6ab084fd9e8b37ddd798aebacf9",
            "output_index": 7,
            "data_hash": null,
            "inline_datum": null,
            "reference_script_hash": null,
            "collateral": false,
            "reference": false
        }
    ],
    "outputs": [
        {
            "address": "addr1q9vncm7ekqdcra7zgxqx7j6xjdhxeslfvgzwkyyyd7z2jnpsu0lk08st4u83scd6fxl7a5rtzlcugqt0epansd5feyqstwvx00",
            "amount": [
                {
                    "unit": "lovelace",
                    "quantity": "33100000"
                }
            ],
            "output_index": 0,
            "data_hash": null,
            "inline_datum": null,
            "collateral": false,
            "reference_script_hash": null
        },
        {
            "address": "Ae2tdPwUPEYz3nGpJ2DWTX71ofHJhDggqXyESe4msrntpUivF5mpGjrWDQg",
            "amount": [
                {
                    "unit": "lovelace",
                    "quantity": "66444456"
                }
            ],
            "output_index": 1,
            "data_hash": null,
            "inline_datum": null,
            "collateral": false,
            "reference_script_hash": null
        },
        {
            "address": "addr1qyc9hqntnsmt6t0jrsf6wyu9qx05hss9ny2zwpng5emkdgrljey6y888yd8p6q707suln9xmy3d058hscden9r9v9cus2l5j49",
            "amount": [
                {
                    "unit": "lovelace",
                    "quantity": "75383436"
                }
            ],
            "output_index": 2,
            "data_hash": null,
            "inline_datum": null,
            "collateral": false,
            "reference_script_hash": null
        },
        {
            "address": "DdzFFzCqrhtA3iWhmRzqTtmLNmgkkUqHpQzjK7Y9zH4nWnYjUuVXrkdGDbL8kb2wL6Yxes1Vo48HhjYU88QmcvAbhjvf4XVjWcZByYQ1",
            "amount": [
                {
                    "unit": "lovelace",
                    "quantity": "2443431112"
                }
            ],
            "output_index": 3,
            "data_hash": null,
            "inline_datum": null,
            "collateral": false,
            "reference_script_hash": null
        },
        {
            "address": "addr1vy00r80d59mzcshusjl9z6f3zkw7ge9a60x8skwmsx6us5sjnr597",
            "amount": [
                {
                    "unit": "lovelace",
                    "quantity": "499000000"
                }
            ],
            "output_index": 4,
            "data_hash": null,
            "inline_datum": null,
            "collateral": false,
            "reference_script_hash": null
        },
        {
            "address": "addr1vyd4mrn3sxtcd9lggspeszf8a4n0gejkp8yuj0qemnc0fpsapcj20",
            "amount": [
                {
                    "unit": "lovelace",
                    "quantity": "1232812000"
                }
            ],
            "output_index": 5,
            "data_hash": null,
            "inline_datum": null,
            "collateral": false,
            "reference_script_hash": null
        },
        {
            "address": "addr1v8ech9n5jmg6za7se4ap4etmuxgx9hgm8lshre0dfewmpls3mek98",
            "amount": [
                {
                    "unit": "lovelace",
                    "quantity": "26000000"
                }
            ],
            "output_index": 6,
            "data_hash": null,
            "inline_datum": null,
            "collateral": false,
            "reference_script_hash": null
        },
        {
            "address": "addr1q9e43rzz45egwyweulsf97ttg4td7dkd0zewzu2h2wuwnqw5qpeql2n5hq7k6pj8p4ekm5ll8uf744gnqnjs9405qkgq4ewk22",
            "amount": [
                {
                    "unit": "lovelace",
                    "quantity": "348250400"
                }
            ],
            "output_index": 7,
            "data_hash": null,
            "inline_datum": null,
            "collateral": false,
            "reference_script_hash": null
        },
        {
            "address": "addr1q86748jrfvsg5jm7e9na0dmzg278pmes8pa8g0w4rpdt7gve9v6gv7v9anzfgnk5r69ky273f7vcxh47zvhm74md6jesju0f5e",
            "amount": [
                {
                    "unit": "lovelace",
                    "quantity": "131395961"
                }
            ],
            "output_index": 8,
            "data_hash": null,
            "inline_datum": null,
            "collateral": false,
            "reference_script_hash": null
        },
        {
            "address": "addr1q9npvns7snm9ycfh07fs9pv8f8ek0fgrxsvsyr9gja9uwkqwq3wh8ycd3n4ulgmjsd7yg99dexmrjn5jvq02zndyl53s2f5xd6",
            "amount": [
                {
                    "unit": "lovelace",
                    "quantity": "137754021"
                }
            ],
            "output_index": 9,
            "data_hash": null,
            "inline_datum": null,
            "collateral": false,
            "reference_script_hash": null
        },
        {
            "address": "addr1q9k4qlyptg8vwytd0yy8vdxpt7m79g2uu65rw82tvmknjjcwq3wh8ycd3n4ulgmjsd7yg99dexmrjn5jvq02zndyl53s6qjvtn",
            "amount": [
                {
                    "unit": "lovelace",
                    "quantity": "275518044"
                }
            ],
            "output_index": 10,
            "data_hash": null,
            "inline_datum": null,
            "collateral": false,
            "reference_script_hash": null
        },
        {
            "address": "addr1qx396zy9g6ctklt7kcqnwz0lmjmutd80qqhsmh94rx768cswq3wh8ycd3n4ulgmjsd7yg99dexmrjn5jvq02zndyl53s9l5zfj",
            "amount": [
                {
                    "unit": "lovelace",
                    "quantity": "312449816"
                }
            ],
            "output_index": 11,
            "data_hash": null,
            "inline_datum": null,
            "collateral": false,
            "reference_script_hash": null
        },
        {
            "address": "addr1q8zwlx3yaucywuy8uyp4lmyuk9z2yrwjreydu42h93dxwwgwq3wh8ycd3n4ulgmjsd7yg99dexmrjn5jvq02zndyl53s6kgctr",
            "amount": [
                {
                    "unit": "lovelace",
                    "quantity": "10096138434"
                }
            ],
            "output_index": 12,
            "data_hash": null,
            "inline_datum": null,
            "collateral": false,
            "reference_script_hash": null
        },
        {
            "address": "addr1q8smtxslt2euhxcuku5m09g8jxzg57p3ucr97jhp908dc5qwq3wh8ycd3n4ulgmjsd7yg99dexmrjn5jvq02zndyl53svunmjg",
            "amount": [
                {
                    "unit": "lovelace",
                    "quantity": "2062639475"
                }
            ],
            "output_index": 13,
            "data_hash": null,
            "inline_datum": null,
            "collateral": false,
            "reference_script_hash": null
        },
        {
            "address": "addr1q8uepgc9v3skd2y3rewhlkzqxa03psmze37nk8kyj6c7z9cwq3wh8ycd3n4ulgmjsd7yg99dexmrjn5jvq02zndyl53sh0qx8y",
            "amount": [
                {
                    "unit": "lovelace",
                    "quantity": "5094414631"
                }
            ],
            "output_index": 14,
            "data_hash": null,
            "inline_datum": null,
            "collateral": false,
            "reference_script_hash": null
        },
        {
            "address": "addr1q88r30s2k4tjxpphggvwnda5ffjnedzml5ela7dg5lgjdgqwq3wh8ycd3n4ulgmjsd7yg99dexmrjn5jvq02zndyl53sx97aka",
            "amount": [
                {
                    "unit": "lovelace",
                    "quantity": "108420072"
                }
            ],
            "output_index": 15,
            "data_hash": null,
            "inline_datum": null,
            "collateral": false,
            "reference_script_hash": null
        },
        {
            "address": "addr1q8gn4nnmhhceuj363w6vfyp9jjn73xxek89qzg4shqes2dgwq3wh8ycd3n4ulgmjsd7yg99dexmrjn5jvq02zndyl53sgv37r3",
            "amount": [
                {
                    "unit": "lovelace",
                    "quantity": "1439811159"
                }
            ],
            "output_index": 16,
            "data_hash": null,
            "inline_datum": null,
            "collateral": false,
            "reference_script_hash": null
        },
        {
            "address": "addr1q9nldngny4l2n6c6vhz8a0k2rllqtuya7ntc4fsl4m0k2pgwq3wh8ycd3n4ulgmjsd7yg99dexmrjn5jvq02zndyl53s5222s2",
            "amount": [
                {
                    "unit": "lovelace",
                    "quantity": "543867920"
                }
            ],
            "output_index": 17,
            "data_hash": null,
            "inline_datum": null,
            "collateral": false,
            "reference_script_hash": null
        }
    ]
}