{
    "hash": "3956aedf5e32a6296513ed0f91874f801b0459fc16927110d3e7c6a96863b5c7",
    "inputs": [
        {
            "address": "addr1qyzkr690kt4np4gcsxqtys2vyygnhlg7n6q8twnul00339g6gmgrqscqqvthzdystdrcxjprtg92sxwhzq76rk92z0ss5g2eae",
            "amount": [
                {
                    "unit": "lovelace",
                    "quantity": "3642623859"
                }
            ],
            "tx_hash": "26af97d27f7ae0271dfd20b2e3064979ff9b4bb5d8956cc5274cd0f35eec8ebc",
            "output_index": 0,
            "data_hash": null,
            "inline_datum": null,
            "reference_script_hash": null,
            "collateral": false,
            "reference": false
        }
    ],
    "outputs": [
        {
            "address": "addr1q8wqv3ame04nrujcj5hhwgqmznejnj8jk7gettw2q52x4t6pamtkwxsf2th88xrz2v400ch28k40nj0vhqhemq6j5mtqvsd9e3",
            "amount": [
                {
                    "unit": "lovelace",
                    "quantity": "3637447446"
                }
            ],
            "output_index": 0,
            "data_hash": null,
            "inline_datum": null,
            "collateral": false,
            "reference_script_hash": null
        },
        {
            "address": "addr1qyzkr690kt4np4gcsxqtys2vyygnhlg7n6q8twnul00339g6gmgrqscqqvthzdystdrcxjprtg92sxwhzq76rk92z0ss5g2eae",
            "amount": [
                {
                    "unit": "lovelace",
                    "quantity": "5000000"
                }
            ],
            "output_index": 1,
            "data_hash": null,
            "inline_datum": null,
            "collateral": false,
            "reference_script_hash": null
        }
    ]
}