{
    "hash": "ae6814fdf010baf2bf3b29982dc30711580150003834e7b8942858e43d4048ed",
    "inputs": [
        {
            "address": "addr1qxjzpgywlgns4rnhuqtdqd4tjsg324df8l8eatw4qa50t2n8s5y6e2tjf8kl9qkdt8tuue4anf0m2hjdnx09x7swdfpqjc9yjd",
            "amount": [
                {
                    "unit": "lovelace",
                    "quantity": "16028605408"
                }
            ],
            "tx_hash": "0c07c8b86b8efc862642dfefaf0dc1f8d518f9972be34ba60b77137647081d57",
            "output_index": 6,
            "data_hash": null,
            "inline_datum": null,
            "reference_script_hash": null,
            "collateral": false,
            "reference": false
        },
        {
            "address": "addr1qxelrwqnw8aeynnx2xc842qvdtcfrjtu9eprlzn7r9eazkr8s5y6e2tjf8kl9qkdt8tuue4anf0m2hjdnx09x7swdfpq0xjs3a",
            "amount": [
                {
                    "unit": "lovelace",
                    "quantity": "1525805545"
                }
            ],
            "tx_hash": "198ba74c049b941b2bbbbc1ea973ab5444d0bdcfd1a7f74a6f5f8d69667c39ab",
            "output_index": 3,
            "data_hash": null,
            "inline_datum": null,
            "reference_script_hash": null,
            "collateral": false,
            "reference": false
        },
        {
            "address": "addr1qy2j75n9lmcla3d8emxkukx6apeap844gzlgzfuwztull9r8s5y6e2tjf8kl9qkdt8tuue4anf0m2hjdnx09x7swdfpquvdf7k",
            "amount": [
                {
                    "unit": "lovelace",
                    "quantity": "39126970"
                }
            ],
            "tx_hash": "297e5fdcc5e66a779d62f39ccddbc3ed3cedd47e7bf55d441c5d8e5b93bafb08",
            "output_index": 15,
            "data_hash": null,
            "inline_datum": null,
            "reference_script_hash": null,
            "collateral": false,
            "reference": false
        },
        {
            "address": "addr1qyjzg93t3j6sygayakeseneraura3eyy2wd76va6m2r4r6m8s5y6e2tjf8kl9qkdt8tuue4anf0m2hjdnx09x7swdfpqt7k0gx",
            "amount": [
                {
                    "unit": "lovelace",
                    "quantity": "1042916370"
                }
            ],
            "tx_hash": "30a9b152ff52d26951bf3daf8fedbdfe3dc2c8c4a88d27ed28a965a8bf01122a",
            "output_index": 1,
            "data_hash": null,
            "inline_datum": null,
            "reference_script_hash": null,
            "collateral": false,
            "reference": false
        },
        {
            "address": "addr1q9crqdxppvwspg0renq4amlvmw2x68ycafann6xqrz2mgyr8s5y6e2tjf8kl9qkdt8tuue4anf0m2hjdnx09x7swdfpq55g44m",
            "amount": [
                {
                    "unit": "lovelace",
                    "quantity": "101515259"
                }
            ],
            "tx_hash": "8c86bd74f8e361c49e7a8d22ae3438d94f139f2f1fdc36ad1339e7f37bbbdb13",
            "output_index": 6,
            "data_hash": null,
            "inline_datum": null,
            "reference_script_hash": null,
            "collateral": false,
            "reference": false
        },
        {
            "address": "addr1qx8e7sdef9jpf543nyv40dkza4ttg3usvdg78qj6m0nsvnn8s5y6e2tjf8kl9qkdt8tuue4anf0m2hjdnx09x7swdfpqkwxgce",
            "amount": [
                {
                    "unit": "lovelace",
                    "quantity": "1025351946"
                }
            ],
            "tx_hash": "8ed845a54801c73b637b4fe569b974d07d2589970ee1a67815a31286a67cc178",
            "output_index": 13,
            "data_hash": null,
            "inline_datum": null,
            "reference_script_hash": null,
            "collateral": false,
            "reference": false
        },
        {
            "address": "addr1qyf0tq454j07jkfaqxzv8et3r8zzsadhqgl0q8j8tay5xyt8s5y6e2tjf8kl9qkdt8tuue4anf0m2hjdnx09x7swdfpqyr0dp9",
            "amount": [
                {
                    "unit": "lovelace",
                    "quantity": "106303970"
                }
            ],
            "tx_hash": "ad4ab00348897e8a21d6e005658aedab51b043b65090da3b385dfe108dc396da",
            "output_index": 8,
            "data_hash": null,
            "inline_datum": null,
            "reference_script_hash": null,
            "collateral": false,
            "reference": false
        }
    ],
    "outputs": [
        {
            "address": "addr1qx0fcufppq842duprhcdcm6jyq95ek9043ct0pdepnp6s6tljey6y888yd8p6q707suln9xmy3d058hscden9r9v9cusghlv48",
            "amount": [
                {
                    "unit": "lovelace",
                    "quantity": "47100000"
                }
            ],
            "output_index": 0,
            "data_hash": null,
            "inline_datum": null,
            "collateral": false,
            "reference_script_hash": null
        },
        {
            "address": "DdzFFzCqrhsf4CpNDWyVLuN5qV18AfzA1kopvxUGw5pKm4tvrw9otfBYd8rgBYrp3GVb5L7V43orh4xbT16cVvq86LUGVV1HQ1qFrR7f",
            "amount": [
                {
                    "unit": "lovelace",
                    "quantity": "649000000"
                }
            ],
            "output_index": 1,
            "data_hash": null,
            "inline_datum": null,
            "collateral": false,
            "reference_script_hash": null
        },
        {
            "address": "addr1qx3pehhx7uvchgdppt2smqzgkukhga4r4rqz72wpgsankeky7pd52vywwmdzkcf2udrazjg0dz7k2zgq5lcl5g9ylkgqdgn48w",
            "amount": [
                {
                    "unit": "lovelace",
                    "quantity": "109000000"
                }
            ],
            "output_index": 2,
            "data_hash": null,
            "inline_datum": null,
            "collateral": false,
            "reference_script_hash": null
        },
        {
            "address": "addr1q9ya2q5cg7uuf4rtjlugeu4pz536hmpl77uxd5lwv3qklmj2nmz5u6qlm0wa7s49ptyyudpgw6czj0l60xptvklfmj8qwvls2c",
            "amount": [
                {
                    "unit": "lovelace",
                    "quantity": "497700000"
                }
            ],
            "output_index": 3,
            "data_hash": null,
            "inline_datum": null,
            "collateral": false,
            "reference_script_hash": null
        },
        {
            "address": "addr1q8cmgxez0x4xlc0474ptax3gegngpf4yha6v4ekhhvpvpx2hc4s7w0j520w0gpa3sacaldt7yfg2pcxqnz8ufxn77ruqkh568n",
            "amount": [
                {
                    "unit": "lovelace",
                    "quantity": "1259876658"
                }
            ],
            "output_index": 4,
            "data_hash": null,
            "inline_datum": null,
            "collateral": false,
            "reference_script_hash": null
        },
        {
            "address": "addr1q8a2nsg5479wel9ngcvdg64k53wxg9gtse6h007ml5e2reflt0zadjhz60vy36scw4up9spqjtdg7crmklejyyvqx9gs0fvvue",
            "amount": [
                {
                    "unit": "lovelace",
                    "quantity": "206814047"
                }
            ],
            "output_index": 5,
            "data_hash": null,
            "inline_datum": null,
            "collateral": false,
            "reference_script_hash": null
        },
        {
            "address": "addr1qx8lfzyejgrkemd4spkykjgn8upfz7ztkgdrp84g4uj7fzjdqpawf728dnx2wsxxzsycvawfjyagxa2ktcc0m3puprzsz7c76c",
            "amount": [
                {
                    "unit": "lovelace",
                    "quantity": "838440000"
                }
            ],
            "output_index": 6,
            "data_hash": null,
            "inline_datum": null,
            "collateral": false,
            "reference_script_hash": null
        },
        {
            "address": "DdzFFzCqrhspYwrB1nMVdqP4NLC46R2Q7mANdxDtbxnLWs32TfECN9KMyWtaQTp94GZ1V5zECJt2G6h9sBEPmdmaFMioHudq2jEpMt3Z",
            "amount": [
                {
                    "unit": "lovelace",
                    "quantity": "243233938"
                }
            ],
            "output_index": 7,
            "data_hash": null,
            "inline_datum": null,
            "collateral": false,
            "reference_script_hash": null
        },
        {
            "address": "addr1qx0wtgmx6mckdvdh38ywmyr48hv04sj9enaekl7kpmgflf3qtsqnp9a3knqv6ech5rf66xxqyfnf5garfk4jkcelz2rqwsq4cl",
            "amount": [
                {
                    "unit": "lovelace",
                    "quantity": "471636934"
                }
            ],
            "output_index": 8,
            "data_hash": null,
            "inline_datum": null,
            "collateral": false,
            "reference_script_hash": null
        },
        {
            "address": "addr1q9y3rhhggjzlxh65j3uz6qfgk3q6mylsuu35e2rjp55w3xgh9ss0wppc6qhpt7e786gg0yt8hd76q4gqct37ze96qfcserhwzd",
            "amount": [
                {
                    "unit": "lovelace",
                    "quantity": "60500000"
                }
            ],
            "output_index": 9,
            "data_hash": null,
            "inline_datum": null,
            "collateral": false,
            "reference_script_hash": null
        },
        {
            "address": "addr1qx9e5ccg58g72z3kgjvdsv47vke3lu5egu9sd0fnvj5tmsn8s5y6e2tjf8kl9qkdt8tuue4anf0m2hjdnx09x7swdfpqrzv74s",
            "amount": [
                {
                    "unit": "lovelace",
                    "quantity": "167295298"
                }
            ],
            "output_index": 10,
            "data_hash": null,
            "inline_datum": null,
            "collateral": false,
            "reference_script_hash": null
        },
        {
            "address": "addr1q9gk66p3sf7dlejmnmx5swuyv8s2r8zutrjt3jnlqgv8ypr8s5y6e2tjf8kl9qkdt8tuue4anf0m2hjdnx09x7swdfpqc7uf6d",
            "amount": [
                {
                    "unit": "lovelace",
                    "quantity": "2292415314"
                }
            ],
            "output_index": 11,
            "data_hash": null,
            "inline_datum": null,
            "collateral": false,
            "reference_script_hash": null
        },
        {
            "address": "addr1q85jh7rslyj97cdlnzk4k09wup8j54a3s8e4qfr82jzgzlt8s5y6e2tjf8kl9qkdt8tuue4anf0m2hjdnx09x7swdfpqg8rqtz",
            "amount": [
                {
                    "unit": "lovelace",
                    "quantity": "385844773"
                }
            ],
            "output_index": 12,
            "data_hash": null,
            "inline_datum": null,
            "collateral": false,
            "reference_script_hash": null
        },
        {
            "address": "addr1qytpdkfutddms06dru6upkft00yv3zyprrexvrtmp0z9mun8s5y6e2tjf8kl9qkdt8tuue4anf0m2hjdnx09x7swdfpqrzve4m",
            "amount": [
                {
                    "unit": "lovelace",
                    "quantity": "1758222494"
                }
            ],
            "output_index": 13,
            "data_hash": null,
            "inline_datum": null,
            "collateral": false,
            "reference_script_hash": null
        },
        {
            "address": "addr1q9fd74rc033n308gku2dfe5xxgjzgjm7angjyk7kg0zqugt8s5y6e2tjf8kl9qkdt8tuue4anf0m2hjdnx09x7swdfpqfz845x",
            "amount": [
                {
                    "unit": "lovelace",
                    "quantity": "4449229094"
                }
            ],
            "output_index": 14,
            "data_hash": null,
            "inline_datum": null,
            "collateral": false,
            "reference_script_hash": null
        },
        {
            "address": "addr1qx06l28jxxp7m62y00eppv3sstg5s720a8x7fa76yzu7hrn8s5y6e2tjf8kl9qkdt8tuue4anf0m2hjdnx09x7swdfpqukjl0v",
            "amount": [
                {
                    "unit": "lovelace",
                    "quantity": "731195477"
                }
            ],
            "output_index": 15,
            "data_hash": null,
            "inline_datum": null,
            "collateral": false,
            "reference_script_hash": null
        },
        {
            "address": "addr1qxjgq4g2ya2whsa6qrp48tgxp46m37rlvwq383krs42r94n8s5y6e2tjf8kl9qkdt8tuue4anf0m2hjdnx09x7swdfpquwesf3",
            "amount": [
                {
                    "unit": "lovelace",
                    "quantity": "2961268506"
                }
            ],
            "output_index": 16,
            "data_hash": null,
            "inline_datum": null,
            "collateral": false,
            "reference_script_hash": null
        },
        {
            "address": "addr1qxp7d6q5vkfkldmaj04a4lfk44tf7rdc9y25mdzgkdnn58t8s5y6e2tjf8kl9qkdt8tuue4anf0m2hjdnx09x7swdfpqhhwmxd",
            "amount": [
                {
                    "unit": "lovelace",
                    "quantity": "859782683"
                }
            ],
            "output_index": 17,
            "data_hash": null,
            "inline_datum": null,
            "collateral": false,
            "reference_script_hash": null
        },
        {
            "address": "addr1qy97p7flvuddfwsectzxw4c7xwq6dvtw0em6tqhpqgzylht8s5y6e2tjf8kl9qkdt8tuue4anf0m2hjdnx09x7swdfpqgppe2n",
            "amount": [
                {
                    "unit": "lovelace",
                    "quantity": "1666201987"
                }
            ],
            "output_index": 18,
            "data_hash": null,
            "inline_datum": null,
            "collateral": false,
            "reference_script_hash": null
        },
        {
            "address": "addr1q9juasg23tgs3xr3x6nl8dynyx68pwtuynwawuqxgnedtjm8s5y6e2tjf8kl9qkdt8tuue4anf0m2hjdnx09x7swdfpqgrvf9w",
            "amount": [
                {
                    "unit": "lovelace",
                    "quantity": "214606492"
                }
            ],
            "output_index": 19,
            "data_hash": null,
            "inline_datum": null,
            "collateral": false,
            "reference_script_hash": null
        }
    ]
}