{
    "hash": "e26e083d6cd45c8d5fa93b301a2573490e532d20647c86fc791941869d04b762",
    "inputs": [
        {
            "address": "addr1q822fjavmzlna7ffnmnvx4jcf4jl8chx8ul69sga2j5j3jm0k5xc3p4kpy0xhx4dnkpch535d3vppz5qjfanexnpc3ps0ft8w5",
            "amount": [
                {
                    "unit": "lovelace",
                    "quantity": "3000000"
                }
            ],
            "tx_hash": "290004090779bf32231195a32ce903b781414affdcdda8ef93cb61f562ebc5ea",
            "output_index": 1,
            "data_hash": null,
            "inline_datum": null,
            "reference_script_hash": null,
            "collateral": false,
            "reference": false
        }
    ],
    "outputs": [
        {
            "address": "addr1q822fjavmzlna7ffnmnvx4jcf4jl8chx8ul69sga2j5j3jm0k5xc3p4kpy0xhx4dnkpch535d3vppz5qjfanexnpc3ps0ft8w5",
            "amount": [
                {
                    "unit": "lovelace",
                    "quantity": "3049799853"
                }
            ],
            "output_index": 0,
            "data_hash": null,
            "inline_datum": null,
            "collateral": false,
            "reference_script_hash": null
        }
    ]
}