{
    "hash": "a7507f8dbadfaca86146291f0174672f58bf2801711138731f954cac9e50515e",
    "inputs": [
        {
            "address": "addr1v8v3auqmw0eszza3ww29ea2pwftuqrqqyu26zvzjq9dt2ncydzvs5",
            "amount": [
                {
                    "unit": "lovelace",
                    "quantity": "505329503"
                }
            ],
            "tx_hash": "03656d3ba3103845be5245c896fb2b7abf2bcbde9c296021354ce53006876153",
            "output_index": 1,
            "data_hash": null,
            "inline_datum": null,
            "reference_script_hash": null,
            "collateral": false,
            "reference": false
        },
        {
            "address": "addr1v8v3auqmw0eszza3ww29ea2pwftuqrqqyu26zvzjq9dt2ncydzvs5",
            "amount": [
                {
                    "unit": "lovelace",
                    "quantity": "246356138"
                }
            ],
            "tx_hash": "e4b9887feeb407cccc456ed17c0949ec7b0259ef632e2fdc9c18aeeadd7da4a2",
            "output_index": 1,
            "data_hash": null,
            "inline_datum": null,
            "reference_script_hash": null,
            "collateral": false,
            "reference": false
        }
    ],
    "outputs": [
        {
            "address": "addr1qyg45qx9aq3z08v00cflawdx2mtautljc0gr2u2cs5thd0mx5uwa85u274prfyeyf4wepgfjc6l60jes04n2wax5eulsl2c07e",
            "amount": [
                {
                    "unit": "lovelace",
                    "quantity": "508317930"
                }
            ],
            "output_index": 0,
            "data_hash": null,
            "inline_datum": null,
            "collateral": false,
            "reference_script_hash": null
        },
        {
            "address": "addr1v8v3auqmw0eszza3ww29ea2pwftuqrqqyu26zvzjq9dt2ncydzvs5",
            "amount": [
                {
                    "unit": "lovelace",
                    "quantity": "243187690"
                }
            ],
            "output_index": 1,
            "data_hash": null,
            "inline_datum": null,
            "collateral": false,
            "reference_script_hash": null
        }
    ]
}