{
    "hash": "4ce1bc7acc4724891b9348c87740761d0756f7e1c40bd1c8a91130cd5053a7e3",
    "inputs": [
        {
            "address": "addr1qy6k9t2z00e96sd7nkpz49jy3mv3q47q863khmauxfmm32phvxerwfkp4d6jgzzt64dr6hth09sps6we4mkrg50fsuashtlmhs",
            "amount": [
                {
                    "unit": "lovelace",
                    "quantity": "1500000000"
                }
            ],
            "tx_hash": "19a877b65aa30b4b903712c065e93c2099220887a960797a49b73bdcaccd33be",
            "output_index": 1,
            "data_hash": null,
            "inline_datum": null,
            "reference_script_hash": null,
            "collateral": false,
            "reference": false
        }
    ],
    "outputs": [
        {
            "address": "addr1qxy0qs68xt6jqavm07m64m47qvhf0hzf4hm30wsz645rfeehvxerwfkp4d6jgzzt64dr6hth09sps6we4mkrg50fsuas255ltl",
            "amount": [
                {
                    "unit": "lovelace",
                    "quantity": "1497825743"
                }
            ],
            "output_index": 0,
            "data_hash": null,
            "inline_datum": null,
            "collateral": false,
            "reference_script_hash": null
        }
    ]
}