{
    "hash": "8cc68ae94b3edd65c14e30aee84108110c49062e782f0cc0b3a6575d6daeb40d",
    "inputs": [
        {
            "address": "addr1qx9p2r2jlfh40v2pdez7j5lplw8gkpvx8v2hg09ypfh4mmm4rmljllp6evz82mf9f6spmx7y3rf7llws2rhtuttg93fq5kmxlh",
            "amount": [
                {
                    "unit": "lovelace",
                    "quantity": "14196712491"
                }
            ],
            "tx_hash": "30544103302ba7d1d9364ba0da0b7d2da298dbb93425db9e01b1199295a8bd79",
            "output_index": 0,
            "data_hash": null,
            "inline_datum": null,
            "reference_script_hash": null,
            "collateral": false,
            "reference": false
        }
    ],
    "outputs": [
        {
            "address": "DdzFFzCqrhsgY7eRMdqGpX53f3LdnuukUzJBVhjhYR4t1ScfUrx9ixVkeov8TPDgCexDwF9CteBCF61ieiD8jKykMiN3iEGZ3Bas4h6K",
            "amount": [
                {
                    "unit": "lovelace",
                    "quantity": "14195000000"
                }
            ],
            "output_index": 0,
            "data_hash": null,
            "inline_datum": null,
            "collateral": false,
            "reference_script_hash": null
        },
        {
            "address": "addr1qx9p2r2jlfh40v2pdez7j5lplw8gkpvx8v2hg09ypfh4mmm4rmljllp6evz82mf9f6spmx7y3rf7llws2rhtuttg93fq5kmxlh",
            "amount": [
                {
                    "unit": "lovelace",
                    "quantity": "1512491"
                }
            ],
            "output_index": 1,
            "data_hash": null,
            "inline_datum": null,
            "collateral": false,
            "reference_script_hash": null
        }
    ]
}